Regbank/regbank32.v
module regBank32 (regSrc0, regSrc1, regDst, regSelSrc0, regSelSrc1, regSelDst, 
                             RDWRBar, CSBar, clk, reset);

output reg[31:0] regSrc0;
output reg[31:0] regSrc1;
input [31:0] regDst ;
input [4:0] regSelSrc0, regSelSrc1, regSelDst ;
input CSBar, RDWRBar, clk , reset ;

integer i;

// Define the register bank 32 bit x 32 locations
    reg [31:0] regBank[0:31];




// Assign the registers based on register selection inputs
    always @(posedge clk)
    begin
    // Negative level triggered reset, will reset
    // all the register bank location to '0'

      if (~reset) 
       for (i=0; i<=31; i=i+1) 
        begin
          regBank[i] <= 0 ;
        end

     if (~CSBar)
      case (RDWRBar)
      // Write to the register bank as RWRBar is low
        1'b0: regBank[regSelDst] <=regDst;
      // Read from the register bank as RDWRBar is high
        1'b1: 
        begin
             regSrc0 <= regBank[regSelSrc0] ;
             regSrc1 <= regBank[regSelSrc1] ;
        end
      //  default: 
      endcase
      else begin
              // will have to assign undefined X
               regSrc0= 32'bx;
               regSrc1= 32'bx;
        end
          
    end
   
endmodule

Regbank/regbank32_tb.v
module regbanktb ();

// Inputs to the 32 x 32 Register Bank
// regSelSrc0, regSelSrc1, regSelDst are the selectors of the
// Register location of Src0, Src1, Dst,
// From ALU perspective Src0, Src1 are inputs
// Dst is the ouput of ALU
// Clk is the positive edge clock
// CSBar is the negative level register bank chip select 
// RDWRBar - RD is positive level, WR is negative level
reg [31:0] regDst ;
reg [4:0] regSelSrc0, regSelSrc1, regSelDst;
reg RDWRBar, CSBar, clk, reset;

// Output of the 32 X 32 Register bank
// These feed the ALU
wire [31:0] regSrc0, regSrc1;
integer i;

regBank32 RegB(.regSrc0(regSrc0), .regSrc1(regSrc1), .regDst(regDst),
.regSelSrc0(regSelSrc0), .regSelSrc1(regSelSrc1), .regSelDst(regSelDst), 
.RDWRBar(RDWRBar), .CSBar(CSBar), .clk(clk), .reset(reset) );

always  #5 clk = ~clk;
initial begin
    $dumpfile("regbank.vcd");
    $dumpvars (0, regbanktb );
     clk = 0;
     regSelDst = 5'b 00000;
     regDst = 32'hFAEAFAEA;
     RDWRBar = 1'b1;
     CSBar = 1'b1;
// Apply reset to the register bank
#2 reset  = 1'b0; 
#7 reset  = 1'b1; // release the reset
     
// Write into location Reg[0] with pattern 8h'FAEAFAEA
    #10 regSelDst = 5'b 00011;
        RDWRBar = 1'b0;
        CSBar = 1'b0;
    $display("T=%d, regSelSrc0=%h, regSelSrc1=%h, regSelDst=%h, RDWRBar=%b, CSBar=%b, regSrc0=%h, regSrc1=%h, regDst=%", $time,regSelSrc0, regSelSrc1,regSelDst,RDWRBar, CSBar, regSrc0,regSrc1,regDst);

//Deselect CS 
   #20 RDWRBar = 1'b1;
        CSBar = 1'b1;
        $display("T=%d, regSelSrc0=%h, regSelSrc1=%h, regSelDst=%h, RDWRBar=%b, CSBar=%b, regSrc0=%h, regSrc1=%h, regDst=%", $time,regSelSrc0, regSelSrc1,regSelDst,RDWRBar, CSBar, regSrc0,regSrc1,regDst);

// Read the value from Reg[0] to regSrc0
    #10 regSelSrc0 = 5'b00011;
        RDWRBar =  1'b 1;
        CSBar   =  1'b 0;
        $display("T=%d, regSelSrc0=%h, regSelSrc1=%h, regSelDst=%h, RDWRBar=%b, CSBar=%b, regSrc0=%h, regSrc1=%h, regDst=%", $time,regSelSrc0, regSelSrc1,regSelDst,RDWRBar, CSBar, regSrc0,regSrc1,regDst);
    #15 CSBar = 1'b1 ;

 // Store all location of RegBank with i*10   
#10 CSBar = 0;
#10
 for (i=0; i <= 31; i=i+1)
 begin
     RDWRBar = 0;
     regSelDst = i;
     regDst  = i * 10;
 #12  RDWRBar = 1'b1;
 end
// Read all the locations of RegBank
 #10
for (i=0; i <= 31; i=i+1)
 begin
     RDWRBar = 1'b1;
     regSelSrc0 = i;
     regSelSrc1 = i; 
  #12 RDWRBar = 1'b0;
 end
#1000 $finish;

end


endmodule

Regbank/regbank.vcd
$date
	Thu Nov 21 17:13:39 2024
$end
$version
	Icarus Verilog
$end
$timescale
	1s
$end
$scope module regbanktb $end
$var wire 32 ! regSrc1 [31:0] $end
$var wire 32 " regSrc0 [31:0] $end
$var reg 1 # CSBar $end
$var reg 1 $ RDWRBar $end
$var reg 1 % clk $end
$var reg 32 & regDst [31:0] $end
$var reg 5 ' regSelDst [4:0] $end
$var reg 5 ( regSelSrc0 [4:0] $end
$var reg 5 ) regSelSrc1 [4:0] $end
$var reg 1 * reset $end
$var integer 32 + i [31:0] $end
$scope module RegB $end
$var wire 1 # CSBar $end
$var wire 1 $ RDWRBar $end
$var wire 1 % clk $end
$var wire 32 , regDst [31:0] $end
$var wire 5 - regSelDst [4:0] $end
$var wire 5 . regSelSrc0 [4:0] $end
$var wire 5 / regSelSrc1 [4:0] $end
$var wire 1 * reset $end
$var reg 32 0 regSrc0 [31:0] $end
$var reg 32 1 regSrc1 [31:0] $end
$var integer 32 2 i [31:0] $end
$upscope $end
$upscope $end
$enddefinitions $end
#0
$dumpvars
bx 2
bx 1
bx 0
bx /
bx .
b0 -
b11111010111010101111101011101010 ,
bx +
x*
bx )
bx (
b0 '
b11111010111010101111101011101010 &
0%
1$
1#
bx "
bx !
$end
#2
0*
#5
b100000 2
1%
#9
1*
#10
0%
#15
1%
#19
0#
0$
b11 '
b11 -
#20
0%
#25
1%
#30
0%
#35
1%
#39
1#
1$
#40
0%
#45
1%
#49
0#
b11 (
b11 .
#50
0%
#55
b11111010111010101111101011101010 "
b11111010111010101111101011101010 0
1%
#60
0%
#64
1#
#65
bx "
bx 0
1%
#70
0%
#74
0#
#75
b11111010111010101111101011101010 "
b11111010111010101111101011101010 0
1%
#80
0%
#84
b0 &
b0 ,
b0 '
b0 -
0$
b0 +
#85
1%
#90
0%
#95
1%
#96
b1010 &
b1010 ,
b1 '
b1 -
b1 +
0$
#100
0%
#105
1%
#108
b10100 &
b10100 ,
b10 '
b10 -
b10 +
0$
#110
0%
#115
1%
#120
0%
b11110 &
b11110 ,
b11 '
b11 -
b11 +
0$
#125
1%
#130
0%
#132
b101000 &
b101000 ,
b100 '
b100 -
b100 +
0$
#135
1%
#140
0%
#144
b110010 &
b110010 ,
b101 '
b101 -
b101 +
0$
#145
1%
#150
0%
#155
1%
#156
b111100 &
b111100 ,
b110 '
b110 -
b110 +
0$
#160
0%
#165
1%
#168
b1000110 &
b1000110 ,
b111 '
b111 -
b111 +
0$
#170
0%
#175
1%
#180
0%
b1010000 &
b1010000 ,
b1000 '
b1000 -
b1000 +
0$
#185
1%
#190
0%
#192
b1011010 &
b1011010 ,
b1001 '
b1001 -
b1001 +
0$
#195
1%
#200
0%
#204
b1100100 &
b1100100 ,
b1010 '
b1010 -
b1010 +
0$
#205
1%
#210
0%
#215
1%
#216
b1101110 &
b1101110 ,
b1011 '
b1011 -
b1011 +
0$
#220
0%
#225
1%
#228
b1111000 &
b1111000 ,
b1100 '
b1100 -
b1100 +
0$
#230
0%
#235
1%
#240
0%
b10000010 &
b10000010 ,
b1101 '
b1101 -
b1101 +
0$
#245
1%
#250
0%
#252
b10001100 &
b10001100 ,
b1110 '
b1110 -
b1110 +
0$
#255
1%
#260
0%
#264
b10010110 &
b10010110 ,
b1111 '
b1111 -
b1111 +
0$
#265
1%
#270
0%
#275
1%
#276
b10100000 &
b10100000 ,
b10000 '
b10000 -
b10000 +
0$
#280
0%
#285
1%
#288
b10101010 &
b10101010 ,
b10001 '
b10001 -
b10001 +
0$
#290
0%
#295
1%
#300
0%
b10110100 &
b10110100 ,
b10010 '
b10010 -
b10010 +
0$
#305
1%
#310
0%
#312
b10111110 &
b10111110 ,
b10011 '
b10011 -
b10011 +
0$
#315
1%
#320
0%
#324
b11001000 &
b11001000 ,
b10100 '
b10100 -
b10100 +
0$
#325
1%
#330
0%
#335
1%
#336
b11010010 &
b11010010 ,
b10101 '
b10101 -
b10101 +
0$
#340
0%
#345
1%
#348
b11011100 &
b11011100 ,
b10110 '
b10110 -
b10110 +
0$
#350
0%
#355
1%
#360
0%
b11100110 &
b11100110 ,
b10111 '
b10111 -
b10111 +
0$
#365
1%
#370
0%
#372
b11110000 &
b11110000 ,
b11000 '
b11000 -
b11000 +
0$
#375
1%
#380
0%
#384
b11111010 &
b11111010 ,
b11001 '
b11001 -
b11001 +
0$
#385
1%
#390
0%
#395
1%
#396
b100000100 &
b100000100 ,
b11010 '
b11010 -
b11010 +
0$
#400
0%
#405
1%
#408
b100001110 &
b100001110 ,
b11011 '
b11011 -
b11011 +
0$
#410
0%
#415
1%
#420
0%
b100011000 &
b100011000 ,
b11100 '
b11100 -
b11100 +
0$
#425
1%
#430
0%
#432
b100100010 &
b100100010 ,
b11101 '
b11101 -
b11101 +
0$
#435
1%
#440
0%
#444
b100101100 &
b100101100 ,
b11110 '
b11110 -
b11110 +
0$
#445
1%
#450
0%
#455
1%
#456
b100110110 &
b100110110 ,
b11111 '
b11111 -
b11111 +
0$
#460
0%
#465
1%
#468
b100000 +
1$
#470
0%
#475
b11110 "
b11110 0
1%
#478
b0 )
b0 /
b0 (
b0 .
b0 +
#480
0%
#485
b0 !
b0 1
b0 "
b0 0
1%
#490
0%
b1 )
b1 /
b1 (
b1 .
b1 +
1$
#495
b1010 !
b1010 1
b1010 "
b1010 0
1%
#500
0%
#502
b10 )
b10 /
b10 (
b10 .
b10 +
1$
#505
b10100 !
b10100 1
b10100 "
b10100 0
1%
#510
0%
#514
b11 )
b11 /
b11 (
b11 .
b11 +
1$
#515
b11110 !
b11110 1
b11110 "
b11110 0
1%
#520
0%
#525
1%
#526
b100 )
b100 /
b100 (
b100 .
b100 +
1$
#530
0%
#535
b101000 !
b101000 1
b101000 "
b101000 0
1%
#538
b101 )
b101 /
b101 (
b101 .
b101 +
1$
#540
0%
#545
b110010 !
b110010 1
b110010 "
b110010 0
1%
#550
0%
b110 )
b110 /
b110 (
b110 .
b110 +
1$
#555
b111100 !
b111100 1
b111100 "
b111100 0
1%
#560
0%
#562
b111 )
b111 /
b111 (
b111 .
b111 +
1$
#565
b1000110 !
b1000110 1
b1000110 "
b1000110 0
1%
#570
0%
#574
b1000 )
b1000 /
b1000 (
b1000 .
b1000 +
1$
#575
b1010000 !
b1010000 1
b1010000 "
b1010000 0
1%
#580
0%
#585
1%
#586
b1001 )
b1001 /
b1001 (
b1001 .
b1001 +
1$
#590
0%
#595
b1011010 !
b1011010 1
b1011010 "
b1011010 0
1%
#598
b1010 )
b1010 /
b1010 (
b1010 .
b1010 +
1$
#600
0%
#605
b1100100 !
b1100100 1
b1100100 "
b1100100 0
1%
#610
0%
b1011 )
b1011 /
b1011 (
b1011 .
b1011 +
1$
#615
b1101110 !
b1101110 1
b1101110 "
b1101110 0
1%
#620
0%
#622
b1100 )
b1100 /
b1100 (
b1100 .
b1100 +
1$
#625
b1111000 !
b1111000 1
b1111000 "
b1111000 0
1%
#630
0%
#634
b1101 )
b1101 /
b1101 (
b1101 .
b1101 +
1$
#635
b10000010 !
b10000010 1
b10000010 "
b10000010 0
1%
#640
0%
#645
1%
#646
b1110 )
b1110 /
b1110 (
b1110 .
b1110 +
1$
#650
0%
#655
b10001100 !
b10001100 1
b10001100 "
b10001100 0
1%
#658
b1111 )
b1111 /
b1111 (
b1111 .
b1111 +
1$
#660
0%
#665
b10010110 !
b10010110 1
b10010110 "
b10010110 0
1%
#670
0%
b10000 )
b10000 /
b10000 (
b10000 .
b10000 +
1$
#675
b10100000 !
b10100000 1
b10100000 "
b10100000 0
1%
#680
0%
#682
b10001 )
b10001 /
b10001 (
b10001 .
b10001 +
1$
#685
b10101010 !
b10101010 1
b10101010 "
b10101010 0
1%
#690
0%
#694
b10010 )
b10010 /
b10010 (
b10010 .
b10010 +
1$
#695
b10110100 !
b10110100 1
b10110100 "
b10110100 0
1%
#700
0%
#705
1%
#706
b10011 )
b10011 /
b10011 (
b10011 .
b10011 +
1$
#710
0%
#715
b10111110 !
b10111110 1
b10111110 "
b10111110 0
1%
#718
b10100 )
b10100 /
b10100 (
b10100 .
b10100 +
1$
#720
0%
#725
b11001000 !
b11001000 1
b11001000 "
b11001000 0
1%
#730
0%
b10101 )
b10101 /
b10101 (
b10101 .
b10101 +
1$
#735
b11010010 !
b11010010 1
b11010010 "
b11010010 0
1%
#740
0%
#742
b10110 )
b10110 /
b10110 (
b10110 .
b10110 +
1$
#745
b11011100 !
b11011100 1
b11011100 "
b11011100 0
1%
#750
0%
#754
b10111 )
b10111 /
b10111 (
b10111 .
b10111 +
1$
#755
b11100110 !
b11100110 1
b11100110 "
b11100110 0
1%
#760
0%
#765
1%
#766
b11000 )
b11000 /
b11000 (
b11000 .
b11000 +
1$
#770
0%
#775
b11110000 !
b11110000 1
b11110000 "
b11110000 0
1%
#778
b11001 )
b11001 /
b11001 (
b11001 .
b11001 +
1$
#780
0%
#785
b11111010 !
b11111010 1
b11111010 "
b11111010 0
1%
#790
0%
b11010 )
b11010 /
b11010 (
b11010 .
b11010 +
1$
#795
b100000100 !
b100000100 1
b100000100 "
b100000100 0
1%
#800
0%
#802
b11011 )
b11011 /
b11011 (
b11011 .
b11011 +
1$
#805
b100001110 !
b100001110 1
b100001110 "
b100001110 0
1%
#810
0%
#814
b11100 )
b11100 /
b11100 (
b11100 .
b11100 +
1$
#815
b100011000 !
b100011000 1
b100011000 "
b100011000 0
1%
#820
0%
#825
1%
#826
b11101 )
b11101 /
b11101 (
b11101 .
b11101 +
1$
#830
0%
#835
b100100010 !
b100100010 1
b100100010 "
b100100010 0
1%
#838
b11110 )
b11110 /
b11110 (
b11110 .
b11110 +
1$
#840
0%
#845
b100101100 !
b100101100 1
b100101100 "
b100101100 0
1%
#850
0%
b11111 )
b11111 /
b11111 (
b11111 .
b11111 +
1$
#855
b100110110 !
b100110110 1
b100110110 "
b100110110 0
1%
#860
0%
#862
b100000 +
0$
