ALU/FA_df.v
// Data flow modelling of full adder
// x,y, cin are the inputs
// s, cout are the outputs
module FA_df (s,cout,x,y,cin);
output s, cout;
input x,y,cin;

assign {cout, s} = x + y + cin;
endmodule

ALU/FA_tb.v
// Test bench to test a full adder
module FA_tb ();
// inputs to the 1-bit full adder
reg a0, b0, cin;
// output of the 1-bit full adder
wire s0, cout;
// counter to generate input vectors of 1-bit adder
reg [3:0] seed;

FA_df FA (.s(s0), .cout(cout),.x(a0),.y(b0),.cin(cin));
initial begin
    $dumpfile("FA_tb.vcd");
    $dumpvars(0,FA_tb);
    $monitor("Time: %0t | a0=%b, b0=%b, cin=%b -> s0=%b, cout=%b", 
             $time, a0, b0, cin, s0, cout);
    #5 a0 = 1'b0;
       b0 = 1'b0;
       cin = 1'b0;
       seed = 3'b000;
    while (seed <= 3'b111) begin
        #5 {b0,a0, cin} = seed ;
        seed = seed + 3'b001;
    end
    #50 $finish ;

end
endmodule

ALU/FA_tb.vcd
$date
	Thu Nov 28 16:37:39 2024
$end
$version
	Icarus Verilog
$end
$timescale
	1s
$end
$scope module FA_tb $end
$var wire 1 ! s0 $end
$var wire 1 " cout $end
$var reg 1 # a0 $end
$var reg 1 $ b0 $end
$var reg 1 % cin $end
$var reg 4 & seed [3:0] $end
$scope module FA $end
$var wire 1 % cin $end
$var wire 1 # x $end
$var wire 1 $ y $end
$var wire 1 ! s $end
$var wire 1 " cout $end
$upscope $end
$upscope $end
$enddefinitions $end
$comment Show the parameter values. $end
$dumpall
$end
#0
$dumpvars
bx &
x%
x$
x#
x"
x!
$end
#5
0!
0"
b0 &
0%
0$
0#
#10
b1 &
#15
1!
b10 &
1%
#20
b11 &
1#
0%
#25
0!
1"
b100 &
1%
#30
1!
0"
b101 &
1$
0#
0%
#35
0!
1"
b110 &
1%
#40
b111 &
1#
0%
#45
1!
b1000 &
1%
